README.md
setup.py
sunnyday/__init__.py
sunnyday/sunnyday.py
weather_forecast_data.egg-info/PKG-INFO
weather_forecast_data.egg-info/SOURCES.txt
weather_forecast_data.egg-info/dependency_links.txt
weather_forecast_data.egg-info/requires.txt
weather_forecast_data.egg-info/top_level.txt