Metadata-Version: 2.1
Name: weather-forecast-data
Version: 1.0.0
Summary: Weather Forecast Data
Home-page: https://github.com/Van-Giang-Pro/Weather_Forecast.git
Author: Văn Giang
Author-email: vangiang260694@gmail.com
License: MIT
Keywords: weather,forecast,openweather
Platform: UNKNOWN
Classifier: Development Status :: 3 - Alpha
Classifier: Intended Audience :: Developers
Classifier: Topic :: Software Development :: Build Tools
Classifier: License :: OSI Approved :: MIT License
Classifier: Programming Language :: Python :: 3.5
Classifier: Programming Language :: Python :: 3.6
Classifier: Programming Language :: Python :: 3.7
Classifier: Programming Language :: Python :: 3.8
